lazyimports_entrypoints/__init__.py
lazyimports_entrypoints/analysis.py
lazyimports_entrypoints/py.typed
lazyimports_entrypoints/hatchling/__init__.py
lazyimports_entrypoints/hatchling/hooks.py
lazyimports_entrypoints/hatchling/lazyimports_hook.py
pylazyimports_eps-0.2.0.dist-info/METADATA
pylazyimports_eps-0.2.0.dist-info/WHEEL
pylazyimports_eps-0.2.0.dist-info/entry_points.txt
pylazyimports_eps-0.2.0.dist-info/RECORD
