Metadata-Version: 2.4
Name: pylazyimports-eps
Version: 0.2.0
Summary: Hatch plugin to automaticilly detect and fill lazyimport entrypoints
Project-URL: Repository, https://github.com/hmiladhia/lazyimports
Project-URL: Issues, https://github.com/hmiladhia/lazyimports/issues
Author: Dhia Hmila
License: MIT License
Classifier: Framework :: Hatch
Classifier: Intended Audience :: Developers
Classifier: License :: OSI Approved :: MIT License
Classifier: Programming Language :: Python
Classifier: Programming Language :: Python :: 3
Classifier: Programming Language :: Python :: 3.10
Classifier: Programming Language :: Python :: 3.11
Classifier: Programming Language :: Python :: 3.12
Classifier: Programming Language :: Python :: 3.13
Classifier: Programming Language :: Python :: 3.14
Classifier: Typing :: Typed
Requires-Python: >=3.10
Requires-Dist: hatchling>=1.0.0
